odoo10_addon_web_unclickable-10.0.1.0.0.99.dev2-py3.8-nspkg.pth
odoo/addons/web_unclickable/README.rst
odoo/addons/web_unclickable/__init__.py
odoo/addons/web_unclickable/__manifest__.py
odoo/addons/web_unclickable/readme/CONTRIBUTORS.rst
odoo/addons/web_unclickable/readme/DESCRIPTION.rst
odoo/addons/web_unclickable/readme/USAGE.rst
odoo/addons/web_unclickable/static/description/icon.png
odoo/addons/web_unclickable/static/description/index.html
odoo/addons/web_unclickable/static/src/css/web_template.css
odoo/addons/web_unclickable/views/web_template.xml
odoo10_addon_web_unclickable-10.0.1.0.0.99.dev2.dist-info/METADATA
odoo10_addon_web_unclickable-10.0.1.0.0.99.dev2.dist-info/WHEEL
odoo10_addon_web_unclickable-10.0.1.0.0.99.dev2.dist-info/namespace_packages.txt
odoo10_addon_web_unclickable-10.0.1.0.0.99.dev2.dist-info/top_level.txt
odoo10_addon_web_unclickable-10.0.1.0.0.99.dev2.dist-info/RECORD
